.DS_Store
lookerapi/__init__.py
lookerapi/api_client.py
lookerapi/configuration.py
lookerapi/rest.py
lookerapi/apis/__init__.py
lookerapi/apis/api_auth_api.py
lookerapi/apis/auth_api.py
lookerapi/apis/config_api.py
lookerapi/apis/connection_api.py
lookerapi/apis/content_api.py
lookerapi/apis/dashboard_api.py
lookerapi/apis/data_action_api.py
lookerapi/apis/datagroup_api.py
lookerapi/apis/group_api.py
lookerapi/apis/homepage_api.py
lookerapi/apis/integration_api.py
lookerapi/apis/look_api.py
lookerapi/apis/lookml_model_api.py
lookerapi/apis/project_api.py
lookerapi/apis/query_api.py
lookerapi/apis/render_task_api.py
lookerapi/apis/role_api.py
lookerapi/apis/running_queries_api.py
lookerapi/apis/scheduled_plan_api.py
lookerapi/apis/session_api.py
lookerapi/apis/space_api.py
lookerapi/apis/sql_query_api.py
lookerapi/apis/user_api.py
lookerapi/apis/user_attribute_api.py
lookerapi/apis/workspace_api.py
lookerapi/models/__init__.py
lookerapi/models/access_filter.py
lookerapi/models/access_token.py
lookerapi/models/api_session.py
lookerapi/models/api_version.py
lookerapi/models/api_version_element.py
lookerapi/models/backup_configuration.py
lookerapi/models/content_favorite.py
lookerapi/models/content_meta.py
lookerapi/models/content_meta_group_user.py
lookerapi/models/content_view.py
lookerapi/models/create_dashboard_render_task.py
lookerapi/models/create_query_task.py
lookerapi/models/credentials_api.py
lookerapi/models/credentials_api3.py
lookerapi/models/credentials_email.py
lookerapi/models/credentials_embed.py
lookerapi/models/credentials_google.py
lookerapi/models/credentials_ldap.py
lookerapi/models/credentials_looker_openid.py
lookerapi/models/credentials_oidc.py
lookerapi/models/credentials_saml.py
lookerapi/models/credentials_totp.py
lookerapi/models/dashboard.py
lookerapi/models/dashboard_base.py
lookerapi/models/dashboard_element.py
lookerapi/models/dashboard_filter.py
lookerapi/models/dashboard_layout.py
lookerapi/models/dashboard_layout_component.py
lookerapi_deprecated-3.0.0.dist-info/LICENSE
lookerapi_deprecated-3.0.0.dist-info/METADATA
lookerapi_deprecated-3.0.0.dist-info/WHEEL
lookerapi_deprecated-3.0.0.dist-info/top_level.txt
lookerapi_deprecated-3.0.0.dist-info/RECORD
