Metadata-Version: 2.1
Name: lookerapi-deprecated
Version: 3.0.0
Summary: Looker API 3.0 Reference
Home-page: https://demo.looker.com:19999/api-docs/index.html
Author: UNKNOWN
Author-email: russelljgarner@gmail.com
License: UNKNOWN
Keywords: Swagger,Looker API 3.0 Reference
Platform: UNKNOWN
Requires-Dist: urllib3 (>=1.15)
Requires-Dist: six (>=1.10)
Requires-Dist: certifi
Requires-Dist: python-dateutil
